{
    "transition_probability": 0.1,
    "tm_parameters": {
        "num_states": 4,
        "input_symbols": [
            "0",
            "1"
        ],
        "blank_symbol": "_",
        "initial_head_position": 1,
        "accepting_states": [
            1,
            2,
            3
        ],
        "transition_function": {
            "1,0": [
                2,
                "0",
                "R"
            ],
            "1,_": [
                1,
                "1",
                "R"
            ],
            "2,0": [
                0,
                "0",
                "L"
            ]
        }
    },
    "input": "00101",
    "execution": {
        "num_steps": 1,
        "result": "rejected"
    },
    "metrics": {
        "equanimity_importance": 0.001953125,
        "equanimity_subsets": -0.6656904220581055,
        "equanimity_subsets_normalized": 0.9992233276367187,
        "entanglement": 4
    },
    "timestamp": "2025-02-10T12:36:37.900493"
}